<?xml version="1.0" encoding="UTF-8" standalone="no"?>
<serialization>
    <std_pair variableName="object" type="pair">
        <first type="vector" size="5">
            <int_0 val="0"/>
            <int_1 val="1"/>
            <int_2 val="2"/>
            <int_3 val="3"/>
            <int_4 val="4"/>
        </first>
        <second type="pair">
            <first type="vector" size="5">
                <int_0 val="5"/>
                <int_1 val="6"/>
                <int_2 val="7"/>
                <int_3 val="8"/>
                <int_4 val="9"/>
            </first>
            <second val="true"/>
        </second>
    </std_pair>
</serialization>
